Guia09_1528633_Andriel_Mark_da_Silva_Pinto/clock_custom.v
// ---------------------------
// clock_custom.v
// ---------------------------
module clock_custom (output reg clk);
    initial begin
        clk = 1'b0;
    end

    always begin
        #12 clk = ~clk; // Toggling the clock every 12 time units
    end
endmodule // clock_custom

Guia09_1528633_Andriel_Mark_da_Silva_Pinto/Guia_0907.v
// ---------------------------
// Nome: Andriel Mark da Silva Pinto
// Numero de Aluno: 1258633
// Matricula: 859093
// ---------------------------
// Guia_0907.v
// ---------------------------

`include "clock_custom.v"

// ---------------------------
// -- pulse generator (8 time units on high level of clock)
// ---------------------------
module pulse (output reg signal, input clock);
    initial begin
        signal = 1'b0; // Inicializa o sinal
    end

    always @(clock) begin
        if (clock) begin // Verifica se o clock está alto
            signal = 1'b1; // Gera o pulso
            #8 signal = 1'b0; // Mantém o pulso por 8 unidades de tempo
        end
    end
endmodule // pulse

// ---------------------------
// -- Testbench para Guia_0907
// ---------------------------
module Guia_0907;
    wire clock;         // Sinal de clock original
    wire pulse_signal;  // Sinal do gerador de pulso

    // Instancia o gerador de clock do clock_custom
    clock_custom clk (clock);

    // Instancia o gerador de pulso sincronizado com o nível alto do clock
    pulse pls (pulse_signal, clock);

    // Início da simulação
    initial begin
        // Gerar arquivo .vcd para visualização no GTKWave
        $dumpfile("Guia_0907.vcd");
        $dumpvars(1, clock, pulse_signal);

        // Finalizar a simulação após 120 unidades de tempo
        #120 $finish;
    end
endmodule // Guia_0907

Guia09_1528633_Andriel_Mark_da_Silva_Pinto/saidas e vcds e vvp/Guia_0907.vcd
$date
	Sun Sep 29 13:48:22 2024
$end
$version
	Icarus Verilog
$end
$timescale
	1s
$end
$scope module Guia_0907 $end
$var wire 1 ! clock $end
$upscope $end
$scope module Guia_0907 $end
$var wire 1 " pulse_signal $end
$upscope $end
$enddefinitions $end
$comment Show the parameter values. $end
$dumpall
$end
#0
$dumpvars
0"
0!
$end
#12
1"
1!
#20
0"
#24
0!
#36
1"
1!
#44
0"
#48
0!
#60
1"
1!
#68
0"
#72
0!
#84
1"
1!
#92
0"
#96
0!
#108
1"
1!
#116
0"
